{
  "_comment": "DO NOT EDIT MANUALLY - See ../../../README.md",
  "name": "awesome-awesomeness",
  "full_name": "bayandin/awesome-awesomeness",
  "owner": "bayandin",
  "private": false,
  "html_url": "https://github.com/bayandin/awesome-awesomeness",
  "description": "A curated list of awesome awesomeness",
  "fork": false,
  "url": "https://api.github.com/repos/bayandin/awesome-awesomeness",
  "languages_url": "https://api.github.com/repos/bayandin/awesome-awesomeness/languages",
  "pulls_url": "https://api.github.com/repos/bayandin/awesome-awesomeness/pulls{/number}",
  "created_at": "2014-07-08T05:44:19Z",
  "updated_at": "2018-09-14T07:28:39Z",
  "pushed_at": "2018-08-30T10:01:58Z",
  "homepage": "",
  "size": 201,
  "stargazers_count": 22152,
  "language": "Ruby",
  "mirror_url": null,
  "archived": false,
  "license": null,
  "default_branch": "master",
  "contributors": {
    "btomashvili": 1,
    "cesardeazevedo": 1,
    "shlomi-noach": 1,
    "mbuczko": 1,
    "tallesl": 1,
    "elburz": 1,
    "stefanbuck": 1,
    "melvin0008": 1,
    "fasouto": 1,
    "kiloreux": 2,
    "mpron": 1,
    "kevinwuhoo": 1,
    "lborgav": 1,
    "hackerkid": 1,
    "dzharii": 1,
    "brabadu": 1,
    "davidstutz": 1,
    "dkhamsing": 1,
    "DeepAnchor": 1,
    "hzoo": 1,
    "maciejczyzewski": 1,
    "tony": 1,
    "justin-j": 1,
    "lukasz-madon": 1,
    "jaspergould": 1,
    "optikfluffel": 1,
    "julienhay": 1,
    "edobashira": 1,
    "davidsonfellipe": 1,
    "rishirdua": 1,
    "dhamaniasad": 1,
    "ahmdrefat": 1,
    "rickboerebach": 1,
    "agsdot": 1,
    "veggiemonk": 1,
    "willianjusten": 1,
    "silky": 1,
    "shime": 1,
    "code-guru": 1,
    "onurakpolat": 1,
    "Fr0sT-Brutal": 1,
    "LewisJEllis": 1,
    "matteocrippa": 1,
    "zenkay": 1,
    "dufferzafar": 1,
    "webpro": 1,
    "numetriclabz": 1,
    "Superbil": 1,
    "hmert": 1,
    "rizo": 1,
    "ellisonleao": 1,
    "busterc": 1,
    "TimothyKlim": 1,
    "jnv": 1,
    "fffaraz": 1,
    "rabbiabram": 1,
    "knutov": 1,
    "tayllan": 1,
    "maxov": 1,
    "quozd": 1,
    "torkale": 1,
    "joeljfischer": 1,
    "mrecachinas": 1,
    "diegocard": 1,
    "JStumpp": 1,
    "l4u": 1,
    "kdabir": 1,
    "razum2um": 1,
    "shevabam": 1,
    "GustavBertram": 2,
    "anggiaj": 2,
    "ellerbrock": 2,
    "tst2005": 2,
    "eugene-g": 2,
    "phongvh": 2,
    "aviaryan": 2,
    "mre": 2,
    "dictcp": 2,
    "vsouza": 2,
    "ashishb": 2,
    "sindresorhus": 2,
    "matiassingers": 2,
    "huyingjie": 2,
    "adius": 2,
    "therebelrobot": 2,
    "itech001": 2,
    "hugo53": 2,
    "kozross": 2,
    "vasili111": 2,
    "svaksha": 2,
    "dreikanter": 2,
    "sumodirjo": 3,
    "xohozu": 3,
    "Hongbo-Miao": 3,
    "caioteixeira": 3,
    "RichardLitt": 3,
    "westurner": 4,
    "Kikobeats": 9,
    "bayandin": 38,
    "m1guelpf": 130,
    "KleoPetroff": 24,
    "assp1r1n3": 14,
    "coreb1t": 1,
    "4xes": 1,
    "alec-c4": 1,
    "aloisdg": 1,
    "alvaroyanes": 1,
    "amir-arad": 1,
    "Lybecker": 1,
    "arbox": 1,
    "artemgurzhii": 1,
    "benoitjadinon": 1,
    "crazy-canux": 1,
    "carlosperate": 1,
    "rabschi": 1,
    "diogo-fernan": 1,
    "vredniy": 1,
    "DovAmir": 1,
    "ebertti": 1,
    "Friz-zy": 1,
    "guillaume-chevalier": 1,
    "gurre": 1,
    "HQarroum": 1,
    "sirredbeard": 1,
    "igorbarinov": 1,
    "JonZeolla": 1,
    "jpetitcolas": 1,
    "TehShrike": 1,
    "teles": 1,
    "joubertredrat": 1,
    "Jolg42": 1,
    "krisskross": 1,
    "lacymorrow": 1,
    "marcobiedermann": 1,
    "paragonbliss": 1,
    "mischah": 1,
    "mortenjust": 1,
    "MostafaNawara": 1,
    "sneg55": 1,
    "pedronveloso": 1,
    "xyNNN": 1,
    "pnowy": 1,
    "ReadmeCritic": 1,
    "Solido": 1,
    "isRuslan": 1,
    "rshipp": 1,
    "shantanu-deshmukh": 1,
    "sobolevn": 1,
    "Hunter-Github": 1,
    "tmrts": 1,
    "thangchung": 1,
    "tomByrer": 1,
    "tulongf": 1,
    "utkuaydin": 1,
    "onqtam": 1,
    "veelenga": 1,
    "tigerneil": 1,
    "bekicot": 1,
    "ZYSzys": 1,
    "coderyi": 1,
    "d1g": 1,
    "hwclass": 1,
    "iCHAIT": 1,
    "kevingo": 1,
    "kud1ing": 1,
    "ljubad": 1,
    "sachin1092": 1,
    "troxler": 1,
    "ty6tu7uytr": 1,
    "xiaobeicn": 1
  },
  "pulls_authors": [
    "trekhleb",
    "shantanu-deshmukh",
    "GustavBertram",
    "alvaroyanes",
    "Solido",
    "thangchung",
    "DovAmir",
    "ZYSzys",
    "Jolg42",
    "Lybecker",
    "westurner",
    "amir-arad",
    "anggiaj",
    "karuppasamy",
    "pnowy",
    "lacymorrow",
    "sirredbeard",
    "tigerneil",
    "carlosperate",
    "bekicot",
    "troxler",
    "LappleApple",
    "sneg55",
    "artemgurzhii",
    "ReadmeCritic",
    "guillaume-chevalier",
    "ellerbrock",
    "TehShrike",
    "tst2005",
    "MostafaNawara",
    "kud1ing",
    "eugene-g",
    "ljubad",
    "Hunter-Github",
    "phongvh",
    "tomByrer",
    "ty6tu7uytr",
    "diogo-fernan",
    "brookshi",
    "EnricoMonese",
    "coreb1t",
    "onqtam",
    "pedronveloso",
    "m1guelpf",
    "4xes",
    "JonZeolla",
    "sumodirjo",
    "mischah",
    "arbox",
    "aviaryan",
    "joubertredrat",
    "veelenga",
    "xohozu",
    "Hongbo-Miao",
    "mre",
    "byung-u",
    "tulongf",
    "xiaobeicn",
    "JiamingSuen",
    "crazy-canux",
    "gurre",
    "sobolevn",
    "ebertti",
    "hwclass",
    "d1g",
    "KrishMunot",
    "Adrion",
    "parro-it",
    "coderyi",
    "mortenjust",
    "assp1r1n3",
    "haiyangjiajian",
    "ghosh",
    "tmrts",
    "benoitjadinon",
    "kevingo",
    "lucasviola",
    "cristianoliveira",
    "paragonbliss",
    "rabschi",
    "utkuaydin",
    "dkhamsing",
    "Friz-zy",
    "HQarroum",
    "blackout314",
    "dreanor",
    "teles",
    "lucasmaiaesilva",
    "cw7",
    "krisskross",
    "dictcp",
    "hsavit1",
    "iCHAIT",
    "J2TEAM",
    "xyNNN",
    "vredniy",
    "Kikobeats",
    "fasouto",
    "webpro",
    "ibaaj",
    "kiloreux",
    "mpron",
    "kevinwuhoo",
    "aleksandar-todorovic",
    "caioteixeira",
    "wcoder",
    "lborgav",
    "hackerkid",
    "paragonie-scott",
    "dzharii",
    "ChristosChristofidis",
    "igorbarinov",
    "allengaller",
    "mauriciovieira",
    "aloisdg",
    "alec-c4",
    "vsouza",
    "isRuslan",
    "ameizi",
    "elburz",
    "jpetitcolas",
    "tkovs",
    "sachin1092",
    "marcobiedermann",
    "rshipp",
    "btomashvili",
    "cesardeazevedo",
    "huyingjie",
    "shlomi-noach",
    "mbuczko",
    "tallesl",
    "willyc20",
    "tony",
    "matiassingers",
    "melvin0008",
    "phanan",
    "phodal",
    "therebelrobot",
    "davidstutz",
    "adius",
    "sotayamashita",
    "sindresorhus",
    "RichardLitt",
    "stefanbuck",
    "justin-j",
    "ashishb",
    "DeepAnchor",
    "fotiDim",
    "brabadu",
    "hzoo",
    "a11y",
    "lukasz-madon",
    "maciejczyzewski",
    "itech001",
    "eriwin",
    "h4cc",
    "kozross",
    "jaspergould",
    "optikfluffel",
    "hugo53",
    "julienhay",
    "juandecarrion",
    "mfpierre",
    "petk",
    "edobashira",
    "parolkar",
    "rishirdua",
    "davidsonfellipe",
    "dhamaniasad",
    "navidkashani",
    "ahmdrefat",
    "skhaz",
    "rickboerebach",
    "vasili111",
    "noteed",
    "veggiemonk",
    "agsdot",
    "willianjusten",
    "silky",
    "shime",
    "kyleterry",
    "code-guru",
    "gianarb",
    "gallandarakhneorg",
    "onurakpolat",
    "russll",
    "wapmorgan",
    "Fr0sT-Brutal",
    "LewisJEllis",
    "akrawchyk",
    "MarcusFulbright",
    "zenkay",
    "dufferzafar",
    "numetriclabz",
    "matteocrippa",
    "Superbil",
    "streeter",
    "dereuromark",
    "philippeowagner",
    "kipusoep",
    "mischapeters",
    "rosarior",
    "unnawut",
    "svaksha",
    "arslanbilal",
    "anildigital",
    "hmert",
    "ryancarson",
    "rizo",
    "dreikanter",
    "ellisonleao",
    "humiaozuzu",
    "leylaKapi",
    "busterc",
    "TimothyKlim",
    "jnv",
    "fffaraz",
    "hitenpratap",
    "knutov",
    "tayllan",
    "maxov",
    "zia-newversion",
    "quozd",
    "rabbiabram",
    "torkale",
    "joeljfischer",
    "unbalancedparentheses",
    "Valien",
    "mrecachinas",
    "walterheck",
    "prodigeni",
    "JStumpp",
    "Wolg",
    "diegocard",
    "l4u",
    "Edubits",
    "kdabir",
    "razum2um",
    "shevabam",
    "geekishmatt"
  ],
  "languages": {
    "Ruby": {
      "bytes": 1783,
      "color": "#701516"
    }
  },
  "fetched_at": "2018-09-14T08:20:33.233Z"
}
