{
  "_comment": "DO NOT EDIT MANUALLY - See ../../../README.md",
  "name": "browserslist",
  "full_name": "browserslist/browserslist",
  "owner": "browserslist",
  "private": false,
  "html_url": "https://github.com/browserslist/browserslist",
  "description": "🦔 Share target browsers between different front-end tools, like Autoprefixer, Stylelint and babel-preset-env",
  "fork": false,
  "url": "https://api.github.com/repos/browserslist/browserslist",
  "languages_url": "https://api.github.com/repos/browserslist/browserslist/languages",
  "pulls_url": "https://api.github.com/repos/browserslist/browserslist/pulls{/number}",
  "created_at": "2014-12-13T19:35:45Z",
  "updated_at": "2018-09-14T09:01:33Z",
  "pushed_at": "2018-09-13T04:59:37Z",
  "homepage": "https://twitter.com/browserslist",
  "size": 1556,
  "stargazers_count": 4098,
  "language": "JavaScript",
  "mirror_url": null,
  "archived": false,
  "license": {
    "key": "mit",
    "name": "MIT License",
    "spdx_id": "MIT",
    "url": "https://api.github.com/licenses/mit",
    "node_id": "MDc6TGljZW5zZTEz"
  },
  "default_branch": "master",
  "organization": {
    "login": "browserslist",
    "id": 37521022,
    "node_id": "MDEyOk9yZ2FuaXphdGlvbjM3NTIxMDIy",
    "avatar_url": "https://avatars0.githubusercontent.com/u/37521022?v=4",
    "gravatar_id": "",
    "url": "https://api.github.com/users/browserslist",
    "html_url": "https://github.com/browserslist",
    "followers_url": "https://api.github.com/users/browserslist/followers",
    "following_url": "https://api.github.com/users/browserslist/following{/other_user}",
    "gists_url": "https://api.github.com/users/browserslist/gists{/gist_id}",
    "starred_url": "https://api.github.com/users/browserslist/starred{/owner}{/repo}",
    "subscriptions_url": "https://api.github.com/users/browserslist/subscriptions",
    "organizations_url": "https://api.github.com/users/browserslist/orgs",
    "repos_url": "https://api.github.com/users/browserslist/repos",
    "events_url": "https://api.github.com/users/browserslist/events{/privacy}",
    "received_events_url": "https://api.github.com/users/browserslist/received_events",
    "type": "Organization",
    "site_admin": false
  },
  "contributors": {
    "dimitarnestorov": 1,
    "sergey48k": 1,
    "chicoxyzzy": 1,
    "joshingmachine": 1,
    "wooorm": 1,
    "Dubprocessor": 1,
    "An-Tu": 1,
    "vostrik": 1,
    "krzysiek1507": 1,
    "megasmack": 1,
    "vaxul": 1,
    "sylvainpolletvillard": 1,
    "pascalduez": 1,
    "marcofugaro": 1,
    "jstrangfeld": 1,
    "ken1987": 1,
    "willnode": 1,
    "wopian": 1,
    "acusti": 1,
    "awkaiser": 1,
    "pop123123123": 1,
    "blicksky": 1,
    "ideryabin": 1,
    "pastelsky": 1,
    "Semigradsky": 1,
    "jamieconnolly": 1,
    "YellowKirby": 1,
    "rmacklin": 1,
    "oigewan": 1,
    "ozio": 1,
    "pieterbeulque": 1,
    "yukulele": 1,
    "shiroginne": 1,
    "ismay": 1,
    "zhulduz": 1,
    "tuures": 1,
    "jrencz": 1,
    "Kilian": 1,
    "brokenmass": 1,
    "Anima-t3d": 1,
    "stepankuzmin": 1,
    "msheakoski": 1,
    "jennylia": 1,
    "jonrohan": 1,
    "dnahodil": 1,
    "kostasmanionis": 1,
    "mdix": 1,
    "hver": 1,
    "DanReyLop": 1,
    "marcvangend": 1,
    "realityking": 1,
    "lukehorvat": 1,
    "xavhan": 1,
    "halfninja": 1,
    "Munter": 1,
    "jaredly": 1,
    "prdolmos": 1,
    "vxsx": 1,
    "MoOx": 1,
    "jamiebuilds": 2,
    "dmfrancisco": 2,
    "Vasfed": 2,
    "exarus": 2,
    "ntwb": 2,
    "in-in": 2,
    "antiflasher": 2,
    "Mattomanka": 2,
    "maksimsemenov": 2,
    "MeoMix": 2,
    "dleve123": 2,
    "iamvdo": 2,
    "BBosman": 2,
    "ben-eb": 3,
    "papandreou": 3,
    "andrepolischuk": 3,
    "evilebottnawi": 4,
    "akx": 4,
    "AleshaOleg": 6,
    "ai": 570
  },
  "pulls_authors": [
    "bdkjones",
    "dimitarnestorov",
    "sergey48k",
    "chicoxyzzy",
    "dotnetCarpenter",
    "Schweinepriester",
    "joshingmachine",
    "wooorm",
    "Dubprocessor",
    "An-Tu",
    "ur300",
    "oalexander",
    "krzysiek1507",
    "jamiebuilds",
    "vostrik",
    "dmfrancisco",
    "megasmack",
    "Vasfed",
    "vaxul",
    "sylvainpolletvillard",
    "pascalduez",
    "evilebottnawi",
    "marcofugaro",
    "jstrangfeld",
    "ken1987",
    "LEW21",
    "willnode",
    "wopian",
    "acusti",
    "exarus",
    "awkaiser",
    "pop123123123",
    "blicksky",
    "pastelsky",
    "ideryabin",
    "Semigradsky",
    "jamieconnolly",
    "ntwb",
    "rmacklin",
    "YellowKirby",
    "oigewan",
    "ozio",
    "pieterbeulque",
    "sudo-suhas",
    "XhmikosR",
    "yukulele",
    "shiroginne",
    "EsrefDurna",
    "jonathantneal",
    "in-in",
    "ismay",
    "zhulduz",
    "vvscode",
    "tuures",
    "akx",
    "ben-eb",
    "jrencz",
    "Kilian",
    "brokenmass",
    "Mattomanka",
    "openlibser",
    "maksimsemenov",
    "AleshaOleg",
    "stepankuzmin",
    "msheakoski",
    "jennylia",
    "jonrohan",
    "papandreou",
    "dnahodil",
    "mdix",
    "kostasmanionis",
    "hikouki",
    "JoshuaWise",
    "MeoMix",
    "hver",
    "dleve123",
    "DanReyLop",
    "marcvangend",
    "realityking",
    "andrepolischuk",
    "lukehorvat",
    "xavhan",
    "halfninja",
    "iamvdo",
    "joeybaker",
    "Munter",
    "jaredly",
    "prdolmos",
    "BBosman",
    "vxsx",
    "MoOx"
  ],
  "languages": {
    "JavaScript": {
      "bytes": 84517,
      "color": "#f1e05a"
    }
  },
  "fetched_at": "2018-09-14T09:11:50.039Z"
}
