{
  "_comment": "DO NOT EDIT MANUALLY - See ../../../README.md",
  "name": "bootstrap",
  "full_name": "adamlaz/bootstrap",
  "owner": "adamlaz",
  "private": false,
  "html_url": "https://github.com/adamlaz/bootstrap",
  "description": "HTML, CSS, and JS toolkit from Twitter",
  "fork": true,
  "url": "https://api.github.com/repos/adamlaz/bootstrap",
  "languages_url": "https://api.github.com/repos/adamlaz/bootstrap/languages",
  "pulls_url": "https://api.github.com/repos/adamlaz/bootstrap/pulls{/number}",
  "created_at": "2012-07-20T14:17:00Z",
  "updated_at": "2013-01-11T07:48:31Z",
  "pushed_at": "2012-07-20T04:25:46Z",
  "homepage": "http://twitter.github.com/bootstrap",
  "size": 17532,
  "stargazers_count": 1,
  "language": "JavaScript",
  "mirror_url": null,
  "archived": false,
  "license": {
    "key": "apache-2.0",
    "name": "Apache License 2.0",
    "spdx_id": "Apache-2.0",
    "url": "https://api.github.com/licenses/apache-2.0",
    "node_id": "MDc6TGljZW5zZTI="
  },
  "default_branch": "master",
  "contributors": {
    "ejain": 1,
    "CaryLandholt": 1,
    "TannerNMO": 1,
    "mshafrir": 1,
    "jarijokinen": 1,
    "amenonsen": 1,
    "MarkReeder": 1,
    "ChadMoran": 1,
    "lukeman": 1,
    "mistermarco": 1,
    "napoleond": 1,
    "xaro": 1,
    "trevyn": 1,
    "scottwater": 1,
    "benoberkfell": 1,
    "gnuwilliam": 1,
    "pkauders": 1,
    "renajohn": 1,
    "billmn": 1,
    "blizzy78": 1,
    "groodt": 1,
    "manveru": 1,
    "jbnunn": 1,
    "piscis": 1,
    "ceejayoz": 1,
    "mkaschenko": 1,
    "leocassarani": 1,
    "JulianBirch": 1,
    "nikcub": 1,
    "avalanche123": 1,
    "southpolesteve": 1,
    "purcell": 1,
    "vecdeque": 1,
    "alepee": 1,
    "adamnbowen": 1,
    "workwithnano": 1,
    "asmega": 1,
    "kasperp": 1,
    "cheeaun": 1,
    "nickveys": 1,
    "soffes": 1,
    "yury": 1,
    "weslly": 1,
    "karthikv": 1,
    "igorbozato": 1,
    "Tigraine": 1,
    "dliuzzi": 1,
    "rafbm": 1,
    "aziz": 2,
    "AlecRust": 2,
    "gruviimark": 2,
    "alexpeattie": 2,
    "deytao": 3,
    "meleyal": 2,
    "inmarelibero": 2,
    "DominikTo": 2,
    "cvrebert": 2,
    "eirikb": 2,
    "nkryptic": 2,
    "linrock": 2,
    "OpenGrid": 2,
    "jwieland": 2,
    "mchung": 2,
    "kevva": 2,
    "sferik": 2,
    "jonathaningram": 2,
    "evnm": 3,
    "martinbean": 2,
    "raulriera": 2,
    "kriansa": 2,
    "matthewpennell": 2,
    "jorgenfb": 3,
    "iamnirav": 3,
    "tierra": 3,
    "wrightlabs": 3,
    "pamelafox": 3,
    "pokonski": 3,
    "Calvein": 3,
    "olvlvl": 3,
    "rvagg": 5,
    "aaronj1335": 3,
    "DHS": 3,
    "MGaetan89": 4,
    "necolas": 4,
    "tinyfly": 4,
    "pthrasher": 4,
    "sankage": 4,
    "SSPMark": 5,
    "ansman": 5,
    "purwandi": 6,
    "andriijas": 7,
    "smaboshe": 7,
    "buraktuyan": 8,
    "cgunther": 7,
    "Synchro": 8,
    "caniszczyk": 8,
    "jacobrask": 8,
    "lookfirst": 8,
    "fat": 696,
    "mdo": 1365,
    "ademaro": 1,
    "bastula": 1,
    "anirvan": 1,
    "jasny": 1,
    "BigBlueHat": 1,
    "billyvg": 1,
    "cwiederspan": 1,
    "dannykeane": 1,
    "davewasmer": 1,
    "et": 1,
    "tagliala": 1,
    "codler": 1,
    "htanata": 1,
    "henrik": 1,
    "zerkms": 1,
    "jmar777": 1,
    "artstorm": 1,
    "jonathanmaron": 1,
    "grantzau": 1,
    "shama": 1,
    "laczoka": 1,
    "luk3thomas": 1,
    "sirlantis": 1,
    "maxbublik": 1,
    "mikaelbr": 1,
    "noahblon": 1,
    "pvorb": 1,
    "finneganh": 1,
    "charettes": 1,
    "tarsisazevedo": 1,
    "tomtastico": 1,
    "tobaco": 1,
    "au-phiware": 1,
    "burningTyger": 1,
    "ctalkington": 1,
    "raphaelz": 1,
    "zhongwei99": 1
  },
  "pulls_authors": [],
  "languages": {},
  "fetched_at": "2018-09-12T15:30:49.572Z"
}
