{
  "_comment": "DO NOT EDIT MANUALLY - See ../../../README.md",
  "name": "meteor-astronomy",
  "full_name": "jagi/meteor-astronomy",
  "owner": "jagi",
  "private": false,
  "html_url": "https://github.com/jagi/meteor-astronomy",
  "description": "Model layer for Meteor",
  "fork": false,
  "url": "https://api.github.com/repos/jagi/meteor-astronomy",
  "languages_url": "https://api.github.com/repos/jagi/meteor-astronomy/languages",
  "pulls_url": "https://api.github.com/repos/jagi/meteor-astronomy/pulls{/number}",
  "created_at": "2015-02-09T08:30:24Z",
  "updated_at": "2018-09-05T04:08:03Z",
  "pushed_at": "2018-07-08T09:14:08Z",
  "homepage": "https://atmospherejs.com/jagi/astronomy",
  "size": 2019,
  "stargazers_count": 582,
  "language": "JavaScript",
  "mirror_url": null,
  "archived": false,
  "license": {
    "key": "mit",
    "name": "MIT License",
    "spdx_id": "MIT",
    "url": "https://api.github.com/licenses/mit",
    "node_id": "MDc6TGljZW5zZTEz"
  },
  "default_branch": "v2",
  "organization": {
    "login": "jagi",
    "id": 33396340,
    "node_id": "MDEyOk9yZ2FuaXphdGlvbjMzMzk2MzQw",
    "avatar_url": "https://avatars1.githubusercontent.com/u/33396340?v=4",
    "gravatar_id": "",
    "url": "https://api.github.com/users/jagi",
    "html_url": "https://github.com/jagi",
    "followers_url": "https://api.github.com/users/jagi/followers",
    "following_url": "https://api.github.com/users/jagi/following{/other_user}",
    "gists_url": "https://api.github.com/users/jagi/gists{/gist_id}",
    "starred_url": "https://api.github.com/users/jagi/starred{/owner}{/repo}",
    "subscriptions_url": "https://api.github.com/users/jagi/subscriptions",
    "organizations_url": "https://api.github.com/users/jagi/orgs",
    "repos_url": "https://api.github.com/users/jagi/repos",
    "events_url": "https://api.github.com/users/jagi/events{/privacy}",
    "received_events_url": "https://api.github.com/users/jagi/received_events",
    "type": "Organization",
    "site_admin": false
  },
  "contributors": {
    "axelvaindal": 1,
    "Faberle": 1,
    "ffxsam": 1,
    "talha-asad": 1,
    "eranbot": 1,
    "erobit": 1,
    "space-alien": 1,
    "ribbedcrown": 1,
    "tdamsma": 1,
    "jbbr": 1,
    "dandv": 1,
    "lukemt": 1,
    "joaorjose": 2,
    "niceilm": 2,
    "joefru": 2,
    "dovrosenberg": 2,
    "awei01": 3,
    "Ben305": 4,
    "peterchoo": 6,
    "lukejagodzinski": 764
  },
  "pulls_authors": [
    "axelvaindal",
    "arggh",
    "james1293",
    "jasonk",
    "mbrobbel",
    "lukejagodzinski",
    "joaorjose",
    "niceilm",
    "Faberle",
    "ffxsam",
    "eranbot",
    "peterchoo",
    "joefru",
    "talha-asad",
    "frco9",
    "Ben305",
    "uzumaxy",
    "s7dhansh",
    "marbemac",
    "krizka",
    "erobit",
    "zvictor",
    "awei01",
    "space-alien",
    "parhelium",
    "ribbedcrown",
    "henry-hz",
    "tdamsma",
    "dovrosenberg",
    "jbbr",
    "dandv",
    "lukemt",
    "gitter-badger"
  ],
  "languages": {
    "JavaScript": {
      "bytes": 249481,
      "color": "#f1e05a"
    }
  },
  "fetched_at": "2018-09-11T23:13:25.267Z"
}
