{
  "_comment": "DO NOT EDIT MANUALLY - See ../../../README.md",
  "name": "generator-aspnet",
  "full_name": "OmniSharp/generator-aspnet",
  "owner": "OmniSharp",
  "private": false,
  "html_url": "https://github.com/OmniSharp/generator-aspnet",
  "description": "yo generator for ASP.NET Core",
  "fork": false,
  "url": "https://api.github.com/repos/OmniSharp/generator-aspnet",
  "languages_url": "https://api.github.com/repos/OmniSharp/generator-aspnet/languages",
  "pulls_url": "https://api.github.com/repos/OmniSharp/generator-aspnet/pulls{/number}",
  "created_at": "2014-12-02T16:28:39Z",
  "updated_at": "2018-09-14T07:56:42Z",
  "pushed_at": "2018-05-23T20:10:20Z",
  "homepage": "",
  "size": 1833,
  "stargazers_count": 899,
  "language": "C#",
  "mirror_url": null,
  "archived": false,
  "license": null,
  "default_branch": "master",
  "organization": {
    "login": "OmniSharp",
    "id": 9420663,
    "node_id": "MDEyOk9yZ2FuaXphdGlvbjk0MjA2NjM=",
    "avatar_url": "https://avatars1.githubusercontent.com/u/9420663?v=4",
    "gravatar_id": "",
    "url": "https://api.github.com/users/OmniSharp",
    "html_url": "https://github.com/OmniSharp",
    "followers_url": "https://api.github.com/users/OmniSharp/followers",
    "following_url": "https://api.github.com/users/OmniSharp/following{/other_user}",
    "gists_url": "https://api.github.com/users/OmniSharp/gists{/gist_id}",
    "starred_url": "https://api.github.com/users/OmniSharp/starred{/owner}{/repo}",
    "subscriptions_url": "https://api.github.com/users/OmniSharp/subscriptions",
    "organizations_url": "https://api.github.com/users/OmniSharp/orgs",
    "repos_url": "https://api.github.com/users/OmniSharp/repos",
    "events_url": "https://api.github.com/users/OmniSharp/events{/privacy}",
    "received_events_url": "https://api.github.com/users/OmniSharp/received_events",
    "type": "Organization",
    "site_admin": false
  },
  "contributors": {
    "lohithgn": 1,
    "SychevIgor": 1,
    "mkoflerAT": 1,
    "celsojr": 1,
    "mauricedb": 1,
    "billpratt": 1,
    "charliethinker": 1,
    "glennular": 1,
    "jorgeavelar": 1,
    "svick": 1,
    "moander": 1,
    "Alber70g": 1,
    "valxv": 1,
    "jwathen": 1,
    "sesispla": 1,
    "tkrotoff": 1,
    "ipinak": 1,
    "stevedesmond-ca": 1,
    "ghuntley": 1,
    "AlexChesser": 1,
    "glennc": 1,
    "francisrath": 1,
    "doggy8088": 1,
    "anthonychu": 1,
    "sandcastle": 1,
    "brsmith9000": 1,
    "TravisTheTechie": 1,
    "nosami": 1,
    "saper": 1,
    "markrendle": 1,
    "frankcash": 1,
    "gavdraper": 1,
    "Gutek": 1,
    "egamma": 1,
    "vcavalcante": 2,
    "PaitoAnderson": 2,
    "marcusoftnet": 2,
    "Yantrio": 2,
    "jpinho": 2,
    "jackjwilliams": 3,
    "horsdal": 3,
    "aeschli": 3,
    "larsw": 3,
    "odytrice": 4,
    "xtianus79": 4,
    "suhasj": 4,
    "jchannon": 5,
    "yukozh": 5,
    "david-driscoll": 9,
    "spboyer": 13,
    "shirhatti": 15,
    "scottaddie": 18,
    "Spinarooni": 25,
    "sayedihashimi": 104,
    "peterblazejewicz": 455
  },
  "pulls_authors": [
    "lohithgn",
    "peterblazejewicz",
    "SychevIgor",
    "mkoflerAT",
    "KrisvanderMast",
    "celsojr",
    "mauricedb",
    "billpratt",
    "vcavalcante",
    "charliethinker",
    "glennular",
    "odytrice",
    "scottaddie",
    "jorgeavelar",
    "svick",
    "moander",
    "Alber70g",
    "julielerman",
    "jchannon",
    "jackjwilliams",
    "Spinarooni",
    "valxv",
    "jwathen",
    "tkrotoff",
    "sesispla",
    "spboyer",
    "horsdal",
    "matteofigus",
    "stuartleeks",
    "ipinak",
    "stevedesmond-ca",
    "ghuntley",
    "AlexChesser",
    "PaitoAnderson",
    "glennc",
    "ahmetb",
    "yukozh",
    "bertt",
    "ninjaboy",
    "rambocoder",
    "smithrobs",
    "david-driscoll",
    "francisrath",
    "shirhatti",
    "doggy8088",
    "anthonychu",
    "markrendle",
    "sandcastle",
    "brsmith9000",
    "marcusoftnet",
    "sayedihashimi",
    "TravisTheTechie",
    "Yantrio",
    "aeschli",
    "nosami",
    "xtianus79",
    "johnpapa",
    "saper",
    "larsw",
    "jpinho",
    "suhasj",
    "frankcash",
    "gavdraper"
  ],
  "languages": {
    "C#": {
      "bytes": 177820,
      "color": "#178600"
    },
    "JavaScript": {
      "bytes": 84591,
      "color": "#f1e05a"
    },
    "F#": {
      "bytes": 8089,
      "color": "#b845fc"
    },
    "CSS": {
      "bytes": 5702,
      "color": "#563d7c"
    }
  },
  "fetched_at": "2018-09-14T09:12:01.366Z"
}
