{
  "_comment": "DO NOT EDIT MANUALLY - See ../../../README.md",
  "name": "scc-debat",
  "full_name": "ultreme/scc-debat",
  "owner": "ultreme",
  "private": false,
  "html_url": "https://github.com/ultreme/scc-debat",
  "description": "Salut c'est cool debat",
  "fork": false,
  "url": "https://api.github.com/repos/ultreme/scc-debat",
  "languages_url": "https://api.github.com/repos/ultreme/scc-debat/languages",
  "pulls_url": "https://api.github.com/repos/ultreme/scc-debat/pulls{/number}",
  "created_at": "2014-12-02T08:42:00Z",
  "updated_at": "2015-02-24T21:29:50Z",
  "pushed_at": "2014-12-02T19:12:47Z",
  "homepage": "http://ultreme.github.io/scc-debat/",
  "size": 128,
  "stargazers_count": 2,
  "language": null,
  "mirror_url": null,
  "archived": false,
  "license": null,
  "default_branch": "gh-pages",
  "organization": {
    "login": "ultreme",
    "id": 8146403,
    "node_id": "MDEyOk9yZ2FuaXphdGlvbjgxNDY0MDM=",
    "avatar_url": "https://avatars0.githubusercontent.com/u/8146403?v=4",
    "gravatar_id": "",
    "url": "https://api.github.com/users/ultreme",
    "html_url": "https://github.com/ultreme",
    "followers_url": "https://api.github.com/users/ultreme/followers",
    "following_url": "https://api.github.com/users/ultreme/following{/other_user}",
    "gists_url": "https://api.github.com/users/ultreme/gists{/gist_id}",
    "starred_url": "https://api.github.com/users/ultreme/starred{/owner}{/repo}",
    "subscriptions_url": "https://api.github.com/users/ultreme/subscriptions",
    "organizations_url": "https://api.github.com/users/ultreme/orgs",
    "repos_url": "https://api.github.com/users/ultreme/repos",
    "events_url": "https://api.github.com/users/ultreme/events{/privacy}",
    "received_events_url": "https://api.github.com/users/ultreme/received_events",
    "type": "Organization",
    "site_admin": false
  },
  "contributors": {
    "moul": 6
  },
  "pulls_authors": [],
  "languages": {},
  "fetched_at": "2018-09-05T13:07:43.282Z"
}
