{
  "_comment": "DO NOT EDIT MANUALLY - See ../../README.md",
  "repos": {
    "smee/dotfiles": {
      "full_name": "smee/dotfiles",
      "name": "dotfiles",
      "stargazers_count": 1,
      "popularity": 0,
      "percentage": 100,
      "maturity": 0,
      "total_commits_count": 40,
      "activity": 5,
      "total_score": 5,
      "total_score_human_formula": "(3 + percentage * 13) * popularity + 2 * maturity + activity",
      "max_total_score": 95
    },
    "cljsjs/packages": {
      "full_name": "cljsjs/packages",
      "name": "packages",
      "stargazers_count": 640,
      "popularity": 3.8056079000859016,
      "percentage": 0.1809720785935884,
      "maturity": 4.584719547505646,
      "total_commits_count": 3868,
      "activity": 5,
      "total_score": 25.675794935627792,
      "total_score_human_formula": "(3 + percentage * 13) * popularity + 2 * maturity + activity",
      "max_total_score": 95
    },
    "dbs-leipzig/gradoop": {
      "full_name": "dbs-leipzig/gradoop",
      "name": "gradoop",
      "stargazers_count": 125,
      "popularity": 3.0938108386557137,
      "percentage": 1.2585812356979404,
      "maturity": 3.9229542320535216,
      "total_commits_count": 874,
      "activity": 5,
      "total_score": 22.633536574957212,
      "total_score_human_formula": "(3 + percentage * 13) * popularity + 2 * maturity + activity",
      "max_total_score": 95
    },
    "http-kit/http-kit": {
      "full_name": "http-kit/http-kit",
      "name": "http-kit",
      "stargazers_count": 1825,
      "popularity": 4.261087729854694,
      "percentage": 0.22271714922049,
      "maturity": 3.613565374531227,
      "total_commits_count": 449,
      "activity": 1.7937020020941037,
      "total_score": 21.927468191250956,
      "total_score_human_formula": "(3 + percentage * 13) * popularity + 2 * maturity + activity",
      "max_total_score": 95
    },
    "smee/binary": {
      "full_name": "smee/binary",
      "name": "binary",
      "stargazers_count": 33,
      "popularity": 2.506543999292103,
      "percentage": 83.69565217391305,
      "maturity": 2.718570715884442,
      "total_commits_count": 92,
      "activity": 1.257453385525661,
      "total_score": 41.48651532920776,
      "total_score_human_formula": "(3 + percentage * 13) * popularity + 2 * maturity + activity",
      "max_total_score": 95
    },
    "smee/jfreechart-utils": {
      "full_name": "smee/jfreechart-utils",
      "name": "jfreechart-utils",
      "stargazers_count": 4,
      "popularity": 1.49139952161816,
      "percentage": 100,
      "maturity": 2.118994386183839,
      "total_commits_count": 53,
      "activity": 1.2578104529526528,
      "total_score": 29.35819157121089,
      "total_score_human_formula": "(3 + percentage * 13) * popularity + 2 * maturity + activity",
      "max_total_score": 95
    },
    "smee/common": {
      "full_name": "smee/common",
      "name": "common",
      "stargazers_count": 2,
      "popularity": 1.0414282204429401,
      "percentage": 100,
      "maturity": 2.118994386183839,
      "total_commits_count": 53,
      "activity": 1.1909890798505938,
      "total_score": 22.091829379305317,
      "total_score_human_formula": "(3 + percentage * 13) * popularity + 2 * maturity + activity",
      "max_total_score": 95
    },
    "venantius/accountant": {
      "full_name": "venantius/accountant",
      "name": "accountant",
      "stargazers_count": 185,
      "popularity": 3.2650928559259493,
      "percentage": 9.523809523809524,
      "maturity": 1.323873088726792,
      "total_commits_count": 42,
      "activity": 1.3228677756984828,
      "total_score": 17.808388437790615,
      "total_score_human_formula": "(3 + percentage * 13) * popularity + 2 * maturity + activity",
      "max_total_score": 95
    },
    "ztellman/virgil": {
      "full_name": "ztellman/virgil",
      "name": "virgil",
      "stargazers_count": 207,
      "popularity": 3.314117061467472,
      "percentage": 2.0408163265306123,
      "maturity": 1.9607586681802867,
      "total_commits_count": 49,
      "activity": 5,
      "total_score": 19.74312406768293,
      "total_score_human_formula": "(3 + percentage * 13) * popularity + 2 * maturity + activity",
      "max_total_score": 95
    },
    "kishanov/re-frame-datatable": {
      "full_name": "kishanov/re-frame-datatable",
      "name": "re-frame-datatable",
      "stargazers_count": 65,
      "popularity": 2.8068970571940928,
      "percentage": 3.5714285714285716,
      "maturity": 0,
      "total_commits_count": 28,
      "activity": 1.0316104246911988,
      "total_score": 10.755503801399305,
      "total_score_human_formula": "(3 + percentage * 13) * popularity + 2 * maturity + activity",
      "max_total_score": 95
    },
    "reagent-project/reagent-forms": {
      "full_name": "reagent-project/reagent-forms",
      "name": "reagent-forms",
      "stargazers_count": 270,
      "popularity": 3.4299527718919838,
      "percentage": 0.373134328358209,
      "maturity": 3.3598608441960054,
      "total_commits_count": 268,
      "activity": 5,
      "total_score": 22.1759583101672,
      "total_score_human_formula": "(3 + percentage * 13) * popularity + 2 * maturity + activity",
      "max_total_score": 95
    },
    "wkf/hawk": {
      "full_name": "wkf/hawk",
      "name": "hawk",
      "stargazers_count": 97,
      "popularity": 2.98276243564867,
      "percentage": 1.694915254237288,
      "maturity": 2.2827606132375395,
      "total_commits_count": 59,
      "activity": 1.826691290511501,
      "total_score": 15.997718665685687,
      "total_score_human_formula": "(3 + percentage * 13) * popularity + 2 * maturity + activity",
      "max_total_score": 95
    },
    "zcaudate-me/lein-repack": {
      "full_name": "zcaudate-me/lein-repack",
      "name": "lein-repack",
      "stargazers_count": 64,
      "popularity": 2.800068385953039,
      "percentage": 2.5641025641025643,
      "maturity": 0,
      "total_commits_count": 39,
      "activity": 0.5723161564709205,
      "total_score": 9.905877442981051,
      "total_score_human_formula": "(3 + percentage * 13) * popularity + 2 * maturity + activity",
      "max_total_score": 95
    },
    "dc-js/dc.js": {
      "full_name": "dc-js/dc.js",
      "name": "dc.js",
      "stargazers_count": 6347,
      "popularity": 4.802545999341932,
      "percentage": 0.036376864314296105,
      "maturity": 4.434561290925249,
      "total_commits_count": 2749,
      "activity": 5,
      "total_score": 28.299471783219854,
      "total_score_human_formula": "(3 + percentage * 13) * popularity + 2 * maturity + activity",
      "max_total_score": 95
    },
    "madvas/fractalify": {
      "full_name": "madvas/fractalify",
      "name": "fractalify",
      "stargazers_count": 100,
      "popularity": 2.996112703696676,
      "percentage": 0.970873786407767,
      "maturity": 2.8017629316450425,
      "total_commits_count": 103,
      "activity": 0.6381271408228137,
      "total_score": 15.608141262271438,
      "total_score_human_formula": "(3 + percentage * 13) * popularity + 2 * maturity + activity",
      "max_total_score": 95
    },
    "smee/icfp00": {
      "full_name": "smee/icfp00",
      "name": "icfp00",
      "stargazers_count": 1,
      "popularity": 0,
      "percentage": 100,
      "maturity": 0,
      "total_commits_count": 3,
      "activity": 0.48757624848642944,
      "total_score": 0.48757624848642944,
      "total_score_human_formula": "(3 + percentage * 13) * popularity + 2 * maturity + activity",
      "max_total_score": 95
    },
    "metosin/ring-swagger": {
      "full_name": "metosin/ring-swagger",
      "name": "ring-swagger",
      "stargazers_count": 321,
      "popularity": 3.505324750586567,
      "percentage": 0.11185682326621924,
      "maturity": 3.9332448375899878,
      "total_commits_count": 894,
      "activity": 1.7950208731999155,
      "total_score": 20.228457083984814,
      "total_score_human_formula": "(3 + percentage * 13) * popularity + 2 * maturity + activity",
      "max_total_score": 95
    },
    "michaelklishin/langohr": {
      "full_name": "michaelklishin/langohr",
      "name": "langohr",
      "stargazers_count": 249,
      "popularity": 3.3946658371709906,
      "percentage": 1.2219959266802445,
      "maturity": 3.9758331384687877,
      "total_commits_count": 982,
      "activity": 1.3982904143813628,
      "total_score": 20.073229020142172,
      "total_score_human_formula": "(3 + percentage * 13) * popularity + 2 * maturity + activity",
      "max_total_score": 95
    },
    "smee/cobyla2": {
      "full_name": "smee/cobyla2",
      "name": "cobyla2",
      "stargazers_count": 2,
      "popularity": 1.0414282204429401,
      "percentage": 91.66666666666667,
      "maturity": 0,
      "total_commits_count": 12,
      "activity": 0.4311942328565195,
      "total_score": 15.965831854463712,
      "total_score_human_formula": "(3 + percentage * 13) * popularity + 2 * maturity + activity",
      "max_total_score": 95
    },
    "htm-community/sanity": {
      "full_name": "htm-community/sanity",
      "name": "sanity",
      "stargazers_count": 50,
      "popularity": 2.6911205011695256,
      "percentage": 0.24213075060532688,
      "maturity": 3.5735611032031995,
      "total_commits_count": 413,
      "activity": 0.8454223400475582,
      "total_score": 16.150614443461816,
      "total_score_human_formula": "(3 + percentage * 13) * popularity + 2 * maturity + activity",
      "max_total_score": 95
    },
    "smee/rpg": {
      "full_name": "smee/rpg",
      "name": "rpg",
      "stargazers_count": 2,
      "popularity": 1.0414282204429401,
      "percentage": 1.1673151750972763,
      "maturity": 3.3383953438818272,
      "total_commits_count": 257,
      "activity": 0.40760554799426085,
      "total_score": 10.366718642601423,
      "total_score_human_formula": "(3 + percentage * 13) * popularity + 2 * maturity + activity",
      "max_total_score": 95
    },
    "ljcoomber/rabbitmq-graphviz": {
      "full_name": "ljcoomber/rabbitmq-graphviz",
      "name": "rabbitmq-graphviz",
      "stargazers_count": 35,
      "popularity": 2.532793353021433,
      "percentage": 62.5,
      "maturity": 0,
      "total_commits_count": 8,
      "activity": 0.4494910671692418,
      "total_score": 28.62681711953268,
      "total_score_human_formula": "(3 + percentage * 13) * popularity + 2 * maturity + activity",
      "max_total_score": 95
    },
    "incanter/incanter": {
      "full_name": "incanter/incanter",
      "name": "incanter",
      "stargazers_count": 2000,
      "popularity": 4.300873605859661,
      "percentage": 0.08984725965858041,
      "maturity": 4.032376351997398,
      "total_commits_count": 1113,
      "activity": 1.7601182172898389,
      "total_score": 22.77772656085479,
      "total_score_human_formula": "(3 + percentage * 13) * popularity + 2 * maturity + activity",
      "max_total_score": 95
    },
    "thebusby/iota": {
      "full_name": "thebusby/iota",
      "name": "iota",
      "stargazers_count": 273,
      "popularity": 3.4347676160681306,
      "percentage": 3.5714285714285716,
      "maturity": 0,
      "total_commits_count": 28,
      "activity": 0.8742801626944816,
      "total_score": 12.773296546930506,
      "total_score_human_formula": "(3 + percentage * 13) * popularity + 2 * maturity + activity",
      "max_total_score": 95
    },
    "luminus-framework/luminus-template": {
      "full_name": "luminus-framework/luminus-template",
      "name": "luminus-template",
      "stargazers_count": 420,
      "popularity": 3.6223567401607295,
      "percentage": 0.12618296529968454,
      "maturity": 4.190692798984685,
      "total_commits_count": 1585,
      "activity": 5,
      "total_score": 24.30787618138164,
      "total_score_human_formula": "(3 + percentage * 13) * popularity + 2 * maturity + activity",
      "max_total_score": 95
    },
    "smee/archive": {
      "full_name": "smee/archive",
      "name": "archive",
      "stargazers_count": 2,
      "popularity": 1.0414282204429401,
      "percentage": 100,
      "maturity": 0,
      "total_commits_count": 15,
      "activity": 0.2501606272118977,
      "total_score": 16.91301215429894,
      "total_score_human_formula": "(3 + percentage * 13) * popularity + 2 * maturity + activity",
      "max_total_score": 95
    },
    "smee/pdf-index": {
      "full_name": "smee/pdf-index",
      "name": "pdf-index",
      "stargazers_count": 2,
      "popularity": 1.0414282204429401,
      "percentage": 100,
      "maturity": 0,
      "total_commits_count": 1,
      "activity": 0.22948188560480887,
      "total_score": 16.89233341269185,
      "total_score_human_formula": "(3 + percentage * 13) * popularity + 2 * maturity + activity",
      "max_total_score": 95
    },
    "smee/exameditor": {
      "full_name": "smee/exameditor",
      "name": "exameditor",
      "stargazers_count": 2,
      "popularity": 1.0414282204429401,
      "percentage": 100,
      "maturity": 3.262045312809844,
      "total_commits_count": 222,
      "activity": 0.21983436538244217,
      "total_score": 23.406776518089174,
      "total_score_human_formula": "(3 + percentage * 13) * popularity + 2 * maturity + activity",
      "max_total_score": 95
    },
    "smee/elateXam": {
      "full_name": "smee/elateXam",
      "name": "elateXam",
      "stargazers_count": 6,
      "popularity": 1.7076084983408428,
      "percentage": 100,
      "maturity": 3.449048808778018,
      "total_commits_count": 320,
      "activity": 0.6114750749882676,
      "total_score": 34.83130866599779,
      "total_score_human_formula": "(3 + percentage * 13) * popularity + 2 * maturity + activity",
      "max_total_score": 95
    },
    "smee/elateXam-logs": {
      "full_name": "smee/elateXam-logs",
      "name": "elateXam-logs",
      "stargazers_count": 1,
      "popularity": 0,
      "percentage": 100,
      "maturity": 0,
      "total_commits_count": 25,
      "activity": 0.1876096384267072,
      "total_score": 0.1876096384267072,
      "total_score_human_formula": "(3 + percentage * 13) * popularity + 2 * maturity + activity",
      "max_total_score": 95
    },
    "technomancy/leiningen": {
      "full_name": "technomancy/leiningen",
      "name": "leiningen",
      "stargazers_count": 6069,
      "popularity": 4.783091817192112,
      "percentage": 0.023803856224708403,
      "maturity": 4.620944429895447,
      "total_commits_count": 4201,
      "activity": 5,
      "total_score": 28.605965595257615,
      "total_score_human_formula": "(3 + percentage * 13) * popularity + 2 * maturity + activity",
      "max_total_score": 95
    },
    "smee/elatexam-demo": {
      "full_name": "smee/elatexam-demo",
      "name": "elatexam-demo",
      "stargazers_count": 1,
      "popularity": 0,
      "percentage": 100,
      "maturity": 0,
      "total_commits_count": 21,
      "activity": 0.15520301857906205,
      "total_score": 0.15520301857906205,
      "total_score_human_formula": "(3 + percentage * 13) * popularity + 2 * maturity + activity",
      "max_total_score": 95
    },
    "smee/elateXam-package": {
      "full_name": "smee/elateXam-package",
      "name": "elateXam-package",
      "stargazers_count": 1,
      "popularity": 0,
      "percentage": 100,
      "maturity": 0,
      "total_commits_count": 11,
      "activity": 0.14104687318268194,
      "total_score": 0.14104687318268194,
      "total_score_human_formula": "(3 + percentage * 13) * popularity + 2 * maturity + activity",
      "max_total_score": 95
    },
    "smee/amor": {
      "full_name": "smee/amor",
      "name": "amor",
      "stargazers_count": 1,
      "popularity": 0,
      "percentage": 100,
      "maturity": 3.3857303922920043,
      "total_commits_count": 282,
      "activity": 0.13676744986353917,
      "total_score": 6.908228234447548,
      "total_score_human_formula": "(3 + percentage * 13) * popularity + 2 * maturity + activity",
      "max_total_score": 95
    },
    "smee/httpbot": {
      "full_name": "smee/httpbot",
      "name": "httpbot",
      "stargazers_count": 2,
      "popularity": 1.0414282204429401,
      "percentage": 100,
      "maturity": 0,
      "total_commits_count": 14,
      "activity": 0.11217351659077135,
      "total_score": 16.775025043677815,
      "total_score_human_formula": "(3 + percentage * 13) * popularity + 2 * maturity + activity",
      "max_total_score": 95
    },
    "smee/amor_updatesite": {
      "full_name": "smee/amor_updatesite",
      "name": "amor_updatesite",
      "stargazers_count": 1,
      "popularity": 0,
      "percentage": 100,
      "maturity": 0,
      "total_commits_count": 8,
      "activity": 0.08975875230739394,
      "total_score": 0.08975875230739394,
      "total_score_human_formula": "(3 + percentage * 13) * popularity + 2 * maturity + activity",
      "max_total_score": 95
    },
    "smee/cewolf": {
      "full_name": "smee/cewolf",
      "name": "cewolf",
      "stargazers_count": 2,
      "popularity": 1.0414282204429401,
      "percentage": 100,
      "maturity": 0,
      "total_commits_count": 4,
      "activity": 0.08944476043613125,
      "total_score": 16.752296287523173,
      "total_score_human_formula": "(3 + percentage * 13) * popularity + 2 * maturity + activity",
      "max_total_score": 95
    },
    "smee/smee.github.com": {
      "full_name": "smee/smee.github.com",
      "name": "smee.github.com",
      "stargazers_count": 1,
      "popularity": 0,
      "percentage": 100,
      "maturity": 0,
      "total_commits_count": 2,
      "activity": 0.07440305805317227,
      "total_score": 0.07440305805317227,
      "total_score_human_formula": "(3 + percentage * 13) * popularity + 2 * maturity + activity",
      "max_total_score": 95
    },
    "smee/wicket-databinder": {
      "full_name": "smee/wicket-databinder",
      "name": "wicket-databinder",
      "stargazers_count": 1,
      "popularity": 0,
      "percentage": 46.15384615384615,
      "maturity": 0,
      "total_commits_count": 13,
      "activity": 0.2196101214566637,
      "total_score": 0.2196101214566637,
      "total_score_human_formula": "(3 + percentage * 13) * popularity + 2 * maturity + activity",
      "max_total_score": 95
    }
  },
  "organizations": [
    "cljsjs",
    "dbs-leipzig",
    "http-kit",
    "reagent-project",
    "zcaudate-me",
    "dc-js",
    "metosin",
    "htm-community",
    "incanter",
    "luminus-framework"
  ]
}
